vecta/__init__.py
vecta/api_client.py
vecta/exceptions.py
vecta/connectors/__init__.py
vecta/connectors/azure_cosmos_connector.py
vecta/connectors/base.py
vecta/connectors/chroma_cloud_connector.py
vecta/connectors/chroma_local_connector.py
vecta/connectors/databricks_connector.py
vecta/connectors/file_store_connector.py
vecta/connectors/langchain_connector.py
vecta/connectors/llama_index_connector.py
vecta/connectors/pgvector_connector.py
vecta/connectors/pinecone_connector.py
vecta/connectors/weaviate_connector.py
vecta/core/__init__.py
vecta/core/benchmark.py
vecta/core/dataset_importer.py
vecta/core/evaluator.py
vecta/core/question_generator.py
vecta/core/schema_helpers.py
vecta/core/schemas.py
vecta/core/similarity.py
vecta-0.1.4.dist-info/licenses/LICENSE
vecta-0.1.4.dist-info/METADATA
vecta-0.1.4.dist-info/WHEEL
vecta-0.1.4.dist-info/top_level.txt
vecta-0.1.4.dist-info/RECORD
