Metadata-Version: 2.4
Name: vecta
Version: 0.1.4
Summary: A lightweight SDK for benchmarking RAG agents
Author-email: Emmett <emmett@runvecta.com>
Maintainer-email: Emmett <emmett@runvecta.com>
License: MIT
Project-URL: Homepage, https://github.com/ctrlfplus/vecta
Project-URL: Documentation, https://vecta.readthedocs.io
Project-URL: Repository, https://github.com/ctrlfplus/vecta.git
Project-URL: Bug Tracker, https://github.com/ctrlfplus/vecta/issues
Keywords: rag,retrieval,vector-database,benchmark,ai,llm
Classifier: Development Status :: 3 - Alpha
Classifier: Intended Audience :: Developers
Classifier: License :: OSI Approved :: MIT License
Classifier: Programming Language :: Python :: 3
Classifier: Programming Language :: Python :: 3.8
Classifier: Programming Language :: Python :: 3.9
Classifier: Programming Language :: Python :: 3.10
Classifier: Programming Language :: Python :: 3.11
Classifier: Programming Language :: Python :: 3.12
Classifier: Topic :: Scientific/Engineering :: Artificial Intelligence
Classifier: Topic :: Software Development :: Libraries :: Python Modules
Requires-Python: >=3.8
License-File: LICENSE
Requires-Dist: jsonpath-ng
Requires-Dist: pydantic>=2.0
Requires-Dist: tqdm
Requires-Dist: numpy
Requires-Dist: pandas
Requires-Dist: requests
Requires-Dist: openai
Requires-Dist: datasets
Provides-Extra: chroma
Requires-Dist: chromadb; extra == "chroma"
Provides-Extra: pinecone
Requires-Dist: pinecone; extra == "pinecone"
Provides-Extra: pgvector
Requires-Dist: psycopg>=3.2.0; extra == "pgvector"
Requires-Dist: pgvector; extra == "pgvector"
Provides-Extra: weaviate
Requires-Dist: weaviate-client; extra == "weaviate"
Provides-Extra: databricks
Requires-Dist: databricks-sdk; extra == "databricks"
Requires-Dist: databricks-vectorsearch; extra == "databricks"
Provides-Extra: azure
Requires-Dist: azure-cosmos; extra == "azure"
Provides-Extra: faiss
Requires-Dist: faiss-cpu; extra == "faiss"
Provides-Extra: langchain
Requires-Dist: langchain-core; extra == "langchain"
Requires-Dist: langchain-community; extra == "langchain"
Requires-Dist: langchain-chroma; extra == "langchain"
Provides-Extra: llamaindex
Requires-Dist: llama_index; extra == "llamaindex"
Provides-Extra: dev
Requires-Dist: pytest; extra == "dev"
Requires-Dist: pandas-stubs; extra == "dev"
Requires-Dist: types-tqdm; extra == "dev"
Requires-Dist: types-requests; extra == "dev"
Requires-Dist: types-reportlab; extra == "dev"
Requires-Dist: python-dotenv; extra == "dev"
Provides-Extra: all
Requires-Dist: pytest; extra == "all"
Requires-Dist: pandas-stubs; extra == "all"
Requires-Dist: types-tqdm; extra == "all"
Requires-Dist: types-requests; extra == "all"
Requires-Dist: types-reportlab; extra == "all"
Requires-Dist: python-dotenv; extra == "all"
Requires-Dist: chromadb; extra == "all"
Requires-Dist: pinecone; extra == "all"
Requires-Dist: psycopg>=3.2.0; extra == "all"
Requires-Dist: pgvector; extra == "all"
Requires-Dist: weaviate-client; extra == "all"
Requires-Dist: databricks-sdk; extra == "all"
Requires-Dist: databricks-vectorsearch; extra == "all"
Requires-Dist: azure-cosmos; extra == "all"
Requires-Dist: faiss-cpu; extra == "all"
Requires-Dist: langchain-core; extra == "all"
Requires-Dist: langchain-community; extra == "all"
Requires-Dist: langchain-chroma; extra == "all"
Requires-Dist: llama_index; extra == "all"
Dynamic: license-file
